keras_adversarial/__init__.py
keras_adversarial/adversarial_model.py
keras_adversarial/adversarial_optimizers.py
keras_adversarial/adversarial_utils.py
keras_adversarial/image_grid.py
keras_adversarial/image_grid_callback.py
keras_adversarial/unrolled_optimizer.py
keras_adversarial/backend/__init__.py
keras_adversarial/backend/tensorflow_backend.py
keras_adversarial/backend/tensorflow_monkeypatch.py
keras_adversarial/backend/theano_backend.py
keras_adversarial-0.0.3.dist-info/DESCRIPTION.rst
keras_adversarial-0.0.3.dist-info/METADATA
keras_adversarial-0.0.3.dist-info/RECORD
keras_adversarial-0.0.3.dist-info/WHEEL
keras_adversarial-0.0.3.dist-info/metadata.json
keras_adversarial-0.0.3.dist-info/top_level.txt
