Metadata-Version: 2.0
Name: keras-adversarial
Version: 0.0.3
Summary: Adversarial models and optimizers for Keras
Home-page: https://github.com/bstriner/keras-adversarial
Author: Ben Striner
Author-email: bstriner@gmail.com
License: MIT
Download-URL: https://github.com/bstriner/keras-adversarial/tarball/v0.0.3
Keywords: keras,gan,adversarial,multiplayer
Platform: UNKNOWN
Classifier: Intended Audience :: Developers
Classifier: License :: OSI Approved :: MIT License
Classifier: Programming Language :: Python :: 2
Classifier: Programming Language :: Python :: 3
Requires-Dist: Keras
